bpwave/__init__.py
bpwave/_version.py
bpwave/io.py
bpwave/py.typed
bpwave/signal.py
bpwave/visu.py
bpwave-0.0.3.dist-info/LICENSE.txt
bpwave-0.0.3.dist-info/METADATA
bpwave-0.0.3.dist-info/WHEEL
bpwave-0.0.3.dist-info/top_level.txt
bpwave-0.0.3.dist-info/RECORD
