Metadata-Version: 2.1
Name: bpwave
Version: 0.0.3
Summary: Blood pressure waveform processing toolbox
Author-email: Répai Attila <repai.attila@hallgato.ppke.hu>
Project-URL: Homepage, https://github.com/repat8/bpwave
Project-URL: Issues, https://github.com/repat8/bpwave/issues
Classifier: Development Status :: 3 - Alpha
Classifier: Programming Language :: Python :: 3.10
Classifier: License :: OSI Approved :: MIT License
Classifier: Operating System :: OS Independent
Classifier: Intended Audience :: Science/Research
Classifier: Typing :: Typed
Requires-Python: >=3.10
License-File: LICENSE.txt
Requires-Dist: h5py
Requires-Dist: matplotlib
Requires-Dist: numpy
Provides-Extra: dev
Requires-Dist: black ; extra == 'dev'
Requires-Dist: black[jupyter] ; extra == 'dev'
Requires-Dist: flake8 ; extra == 'dev'
Requires-Dist: isort ; extra == 'dev'
Requires-Dist: mypy ; extra == 'dev'
Provides-Extra: docs
Requires-Dist: sphinx ; extra == 'docs'
Requires-Dist: sphinx-rtd-theme >=1 ; extra == 'docs'
Provides-Extra: tests
Requires-Dist: pytest ; extra == 'tests'
Requires-Dist: pytest-cov ; extra == 'tests'
